<?xml version="1.0" encoding="UTF-8" standalone="no" ?>
<p1:sbgn xmlns:p1="http://sbgn.org/libsbgn/0.2">

  <p1:map language="activity flow">
    <p1:glyph class="biological activity" id="qual_PSENEN" orientation="horizontal">
      <p1:label text="PSENEN"/>
      <p1:bbox h="27" w="56" x="388.314" y="265.714"/>
    </p1:glyph>
    <p1:glyph class="biological activity" id="qual_PSEN" orientation="horizontal">
      <p1:label text="PSEN"/>
      <p1:bbox h="27" w="56" x="693.619" y="594.714"/>
    </p1:glyph>
    <p1:glyph class="biological activity" id="qual_NCSTN" orientation="horizontal">
      <p1:label text="NCSTN"/>
      <p1:bbox h="27" w="56" x="312.314" y="312.714"/>
    </p1:glyph>
    <p1:glyph class="biological activity" id="qual_APH1A" orientation="horizontal">
      <p1:label text="APH1A"/>
      <p1:bbox h="27" w="56" x="417.667" y="359.714"/>
    </p1:glyph>
    <p1:glyph class="biological activity" id="qual_BACE" orientation="horizontal">
      <p1:label text="BACE"/>
      <p1:bbox h="27" w="56" x="464.314" y="218.714"/>
    </p1:glyph>
    <p1:glyph class="biological activity" id="qual_ADAM1" orientation="horizontal">
      <p1:label text="ADAM1"/>
      <p1:bbox h="27" w="56" x="404" y="30.7143"/>
    </p1:glyph>
    <p1:glyph class="biological activity" id="qual_TNF" orientation="horizontal">
      <p1:label text="TNF"/>
      <p1:bbox h="27" w="56" x="204.333" y="811.6"/>
    </p1:glyph>
    <p1:glyph class="biological activity" id="qual_APP" orientation="horizontal">
      <p1:label text="APP"/>
      <p1:bbox h="27" w="56" x="252" y="185"/>
    </p1:glyph>
    <p1:glyph class="biological activity" id="qual_CASP9" orientation="horizontal">
      <p1:label text="CASP9"/>
      <p1:bbox h="27" w="56" x="845.619" y="457.714"/>
    </p1:glyph>
    <p1:glyph class="biological activity" id="qual_CASP3" orientation="horizontal">
      <p1:label text="CASP3"/>
      <p1:bbox h="27" w="56" x="921.619" y="410.714"/>
    </p1:glyph>
    <p1:glyph class="biological activity" id="qual_CYCS" orientation="horizontal">
      <p1:label text="CYCS"/>
      <p1:bbox h="27" w="56" x="745.302" y="359.714"/>
    </p1:glyph>
    <p1:glyph class="biological activity" id="qual_APAF1" orientation="horizontal">
      <p1:label text="APAF1"/>
      <p1:bbox h="27" w="56" x="769.619" y="453.714"/>
    </p1:glyph>
    <p1:glyph class="biological activity" id="qual_NDUF" orientation="horizontal">
      <p1:label text="NDUF"/>
      <p1:bbox h="27" w="56" x="616.314" y="124.714"/>
    </p1:glyph>
    <p1:glyph class="biological activity" id="qual_SDH" orientation="horizontal">
      <p1:label text="SDH"/>
      <p1:bbox h="27" w="56" x="540.314" y="171.714"/>
    </p1:glyph>
    <p1:glyph class="biological activity" id="qual_UQCRC2" orientation="horizontal">
      <p1:label text="UQCRC2"/>
      <p1:bbox h="27" w="56" x="645.667" y="218.714"/>
    </p1:glyph>
    <p1:glyph class="biological activity" id="qual_ATP" orientation="horizontal">
      <p1:label text="ATP"/>
      <p1:bbox h="27" w="56" x="493.667" y="312.714"/>
    </p1:glyph>
    <p1:glyph class="biological activity" id="qual_COX" orientation="horizontal">
      <p1:label text="COX"/>
      <p1:bbox h="27" w="56" x="569.667" y="265.714"/>
    </p1:glyph>
    <p1:glyph class="biological activity" id="qual_RYR3" orientation="horizontal">
      <p1:label text="RYR3"/>
      <p1:bbox h="27" w="56" x="541.619" y="594.714"/>
    </p1:glyph>
    <p1:glyph class="biological activity" id="qual_ITPR" orientation="horizontal">
      <p1:label text="ITPR"/>
      <p1:bbox h="27" w="56" x="465.619" y="641.714"/>
    </p1:glyph>
    <p1:glyph class="biological activity" id="qual_ATP2A" orientation="horizontal">
      <p1:label text="ATP2A"/>
      <p1:bbox h="27" w="56" x="837.619" y="547.714"/>
    </p1:glyph>
    <p1:glyph class="biological activity" id="qual_GNAQ" orientation="horizontal">
      <p1:label text="GNAQ"/>
      <p1:bbox h="27" w="56" x="313.619" y="596.6"/>
    </p1:glyph>
    <p1:glyph class="biological activity" id="qual_PLCB" orientation="horizontal">
      <p1:label text="PLCB"/>
      <p1:bbox h="27" w="56" x="389.619" y="643.6"/>
    </p1:glyph>
    <p1:glyph class="biological activity" id="qual_Ins145P3" orientation="horizontal">
      <p1:label text="Ins(1,4,5)P3"/>
      <p1:bbox h="23" w="88" x="465.619" y="690.6"/>
    </p1:glyph>
    <p1:glyph class="biological activity" id="qual_GRIN" orientation="horizontal">
      <p1:label text="GRIN"/>
      <p1:bbox h="27" w="56" x="237.619" y="643.6"/>
    </p1:glyph>
    <p1:glyph class="biological activity" id="qual_CACNA1" orientation="horizontal">
      <p1:label text="CACNA1"/>
      <p1:bbox h="27" w="56" x="161.619" y="690.6"/>
    </p1:glyph>
    <p1:glyph class="biological activity" id="qual_Ca2" orientation="horizontal">
      <p1:label text="Ca2+"/>
      <p1:bbox h="23" w="48" x="769.619" y="504.714"/>
    </p1:glyph>
    <p1:glyph class="biological activity" id="qual_HSD17B10" orientation="horizontal">
      <p1:label text="HSD17B10"/>
      <p1:bbox h="27" w="56" x="593.302" y="359.714"/>
    </p1:glyph>
    <p1:glyph class="biological activity" id="qual_CAPN" orientation="horizontal">
      <p1:label text="CAPN"/>
      <p1:bbox h="27" w="56" x="372.86" y="733.6"/>
    </p1:glyph>
    <p1:glyph class="biological activity" id="qual_CDK5R1" orientation="horizontal">
      <p1:label text="CDK5R1"/>
      <p1:bbox h="27" w="56" x="497.86" y="846.714"/>
    </p1:glyph>
    <p1:glyph class="biological activity" id="qual_CDK5" orientation="horizontal">
      <p1:label text="CDK5"/>
      <p1:bbox h="27" w="56" x="421.86" y="893.714"/>
    </p1:glyph>
    <p1:glyph class="biological activity" id="qual_MAPT" orientation="horizontal">
      <p1:label text="MAPT"/>
      <p1:bbox h="27" w="56" x="649.86" y="842.714"/>
    </p1:glyph>
    <p1:glyph class="biological activity" id="qual_TNFRSF1A" orientation="horizontal">
      <p1:label text="TNFRSF1A"/>
      <p1:bbox h="27" w="56" x="267.286" y="455.6"/>
    </p1:glyph>
    <p1:glyph class="biological activity" id="qual_FADD" orientation="horizontal">
      <p1:label text="FADD"/>
      <p1:bbox h="27" w="56" x="343.286" y="502.6"/>
    </p1:glyph>
    <p1:glyph class="biological activity" id="qual_CASP8" orientation="horizontal">
      <p1:label text="CASP8"/>
      <p1:bbox h="27" w="56" x="419.286" y="549.6"/>
    </p1:glyph>
    <p1:glyph class="biological activity" id="qual_BID" orientation="horizontal">
      <p1:label text="BID"/>
      <p1:bbox h="27" w="56" x="495.286" y="406.714"/>
    </p1:glyph>
    <p1:glyph class="biological activity" id="qual_MAPK" orientation="horizontal">
      <p1:label text="MAPK"/>
      <p1:bbox h="27" w="56" x="617.619" y="547.714"/>
    </p1:glyph>
    <p1:glyph class="phenotype" id="qual_Oxidative_phosphorylation" orientation="horizontal">
      <p1:label text="Oxidative phosphorylation"/>
      <p1:bbox h="44" w="123" x="692.314" y="60.7143"/>
    </p1:glyph>
    <p1:glyph class="phenotype" id="qual_Apoptosis" orientation="horizontal">
      <p1:label text="Apoptosis"/>
      <p1:bbox h="35" w="123" x="997.619" y="355.714"/>
    </p1:glyph>
    <p1:glyph class="phenotype" id="qual_Calcium_signaling_pathway" orientation="horizontal">
      <p1:label text="Calcium signaling&#xA;pathway"/>
      <p1:bbox h="44" w="123" x="448.86" y="735.714"/>
    </p1:glyph>
    <p1:glyph class="biological activity" id="qual_NOS1" orientation="horizontal">
      <p1:label text="NOS1"/>
      <p1:bbox h="27" w="56" x="372.86" y="799.714"/>
    </p1:glyph>
    <p1:glyph class="biological activity" id="qual_NO" orientation="horizontal">
      <p1:label text="NO"/>
      <p1:bbox h="23" w="38" x="591.86" y="799.714"/>
    </p1:glyph>
    <p1:glyph class="biological activity" id="qual_Peroxynitrite" orientation="horizontal">
      <p1:label text="Peroxynitrite"/>
      <p1:bbox h="23" w="93" x="725.86" y="799.714"/>
    </p1:glyph>
    <p1:glyph class="biological activity" id="qual_EIF2AK3" orientation="horizontal">
      <p1:label text="EIF2AK3"/>
      <p1:bbox h="27" w="56" x="643.6" y="688.714"/>
    </p1:glyph>
    <p1:glyph class="biological activity" id="qual_ERN1" orientation="horizontal">
      <p1:label text="ERN1"/>
      <p1:bbox h="27" w="56" x="769.619" y="641.714"/>
    </p1:glyph>
    <p1:glyph class="biological activity" id="qual_ATF6" orientation="horizontal">
      <p1:label text="ATF6"/>
      <p1:bbox h="27" w="56" x="845.619" y="688.714"/>
    </p1:glyph>
    <p1:glyph class="biological activity" id="qual_APOE" orientation="horizontal">
      <p1:label text="APOE"/>
      <p1:bbox h="27" w="56" x="84.3143" y="408.6"/>
    </p1:glyph>
    <p1:glyph class="biological activity" id="qual_CALM" orientation="horizontal">
      <p1:label text="CALM"/>
      <p1:bbox h="27" w="56" x="571.286" y="453.714"/>
    </p1:glyph>
    <p1:glyph class="biological activity" id="qual_CHP2" orientation="horizontal">
      <p1:label text="CHP2"/>
      <p1:bbox h="27" w="56" x="693.619" y="500.714"/>
    </p1:glyph>
    <p1:glyph class="biological activity" id="qual_BAD" orientation="horizontal">
      <p1:label text="BAD"/>
      <p1:bbox h="27" w="56" x="669.302" y="406.714"/>
    </p1:glyph>
    <p1:glyph class="biological activity" id="qual_IDE" orientation="horizontal">
      <p1:label text="IDE"/>
      <p1:bbox h="27" w="56" x="156.643" y="156.6"/>
    </p1:glyph>
    <p1:glyph class="biological activity" id="qual_MME" orientation="horizontal">
      <p1:label text="MME"/>
      <p1:bbox h="27" w="56" x="80.6429" y="203.6"/>
    </p1:glyph>
    <p1:glyph class="biological activity" id="qual_APBB1" orientation="horizontal">
      <p1:label text="APBB1"/>
      <p1:bbox h="27" w="56" x="404" y="124.714"/>
    </p1:glyph>
    <p1:glyph class="biological activity" id="qual_LRP1" orientation="horizontal">
      <p1:label text="LRP1"/>
      <p1:bbox h="27" w="56" x="236.314" y="297.6"/>
    </p1:glyph>
    <p1:glyph class="biological activity" id="qual_LPL" orientation="horizontal">
      <p1:label text="LPL"/>
      <p1:bbox h="27" w="56" x="160.314" y="250.6"/>
    </p1:glyph>
    <p1:glyph class="biological activity" id="qual_GAPDH" orientation="horizontal">
      <p1:label text="GAPDH"/>
      <p1:bbox h="27" w="56" x="328" y="171.714"/>
    </p1:glyph>
    <p1:glyph class="biological activity" id="qual_NAE1" orientation="horizontal">
      <p1:label text="NAE1"/>
      <p1:bbox h="27" w="56" x="328" y="77.7143"/>
    </p1:glyph>
    <p1:glyph class="biological activity" id="qual_CASP7" orientation="horizontal">
      <p1:label text="CASP7"/>
      <p1:bbox h="27" w="56" x="725.86" y="889.714"/>
    </p1:glyph>
    <p1:glyph class="biological activity" id="qual_GSK3B" orientation="horizontal">
      <p1:label text="GSK3B"/>
      <p1:bbox h="27" w="56" x="573.86" y="889.714"/>
    </p1:glyph>
    <p1:glyph class="biological activity" id="qual_SNCA" orientation="horizontal">
      <p1:label text="SNCA"/>
      <p1:bbox h="27" w="56" x="122" y="513"/>
    </p1:glyph>
    <p1:glyph class="biological activity" id="qual_IL1B" orientation="horizontal">
      <p1:label text="IL1B"/>
      <p1:bbox h="27" w="56" x="128.333" y="858.6"/>
    </p1:glyph>
    <p1:glyph class="biological activity" id="qual_H2O2" orientation="horizontal">
      <p1:label text="H2O2"/>
      <p1:bbox h="23" w="48" x="280.333" y="768.6"/>
    </p1:glyph>
    <p1:glyph class="biological activity" id="qual_Cu" orientation="horizontal">
      <p1:label text="Cu+"/>
      <p1:bbox h="23" w="43" x="30.6186" y="682.6"/>
    </p1:glyph>
    <p1:glyph class="biological activity" id="qual_Fe2" orientation="horizontal">
      <p1:label text="Fe2+"/>
      <p1:bbox h="23" w="48" x="93.6186" y="725.6"/>
    </p1:glyph>
    <p1:glyph class="biological activity" id="qual_undefined" orientation="horizontal">
      <p1:label text="undefined"/>
      <p1:bbox h="44" w="56" x="160.314" y="344.6"/>
    </p1:glyph>
    <p1:arc class="unknown influence" id="tr_0" source="qual_APP" target="qual_NAE1">
      <p1:start x="294" y="185"/>
      <p1:end x="342" y="104.714"/>
    </p1:arc>
    <p1:arc class="unknown influence" id="tr_1" source="qual_APP" target="qual_APBB1">
      <p1:start x="308" y="198.5"/>
      <p1:end x="404" y="138.214"/>
    </p1:arc>
    <p1:arc class="positive influence" id="tr_2" source="qual_undefined" target="qual_LRP1">
      <p1:start x="202.314" y="344.6"/>
      <p1:end x="250.314" y="324.6"/>
    </p1:arc>
    <p1:arc class="positive influence" id="tr_3" source="qual_TNFRSF1A" target="qual_FADD">
      <p1:start x="309.286" y="482.6"/>
      <p1:end x="357.286" y="502.6"/>
    </p1:arc>
    <p1:arc class="positive influence" id="tr_4" source="qual_FADD" target="qual_CASP8">
      <p1:start x="385.286" y="529.6"/>
      <p1:end x="433.286" y="549.6"/>
    </p1:arc>
    <p1:arc class="positive influence" id="tr_5" source="qual_CASP8" target="qual_BID">
      <p1:start x="461.286" y="549.6"/>
      <p1:end x="509.286" y="433.714"/>
    </p1:arc>
    <p1:arc class="positive influence" id="tr_6" source="qual_GNAQ" target="qual_PLCB">
      <p1:start x="355.619" y="623.6"/>
      <p1:end x="403.619" y="643.6"/>
    </p1:arc>
    <p1:arc class="positive influence" id="tr_7" source="qual_PLCB" target="qual_Ins145P3">
      <p1:start x="445.619" y="657.1"/>
      <p1:end x="487.619" y="690.6"/>
    </p1:arc>
    <p1:arc class="positive influence" id="tr_8" source="qual_CALM" target="qual_CHP2">
      <p1:start x="627.286" y="467.214"/>
      <p1:end x="693.619" y="514.214"/>
    </p1:arc>
    <p1:arc class="positive influence" id="tr_9" source="qual_CHP2" target="qual_BAD">
      <p1:start x="721.619" y="500.714"/>
      <p1:end x="697.302" y="433.714"/>
    </p1:arc>
    <p1:arc class="positive influence" id="tr_10" source="qual_CYCS" target="qual_CASP9">
      <p1:start x="787.302" y="386.714"/>
      <p1:end x="859.619" y="457.714"/>
    </p1:arc>
    <p1:arc class="positive influence" id="tr_11" source="qual_APAF1" target="qual_CASP9">
      <p1:start x="825.619" y="467.214"/>
      <p1:end x="845.619" y="471.214"/>
    </p1:arc>
    <p1:arc class="positive influence" id="tr_12" source="qual_CASP9" target="qual_CASP3">
      <p1:start x="887.619" y="457.714"/>
      <p1:end x="935.619" y="437.714"/>
    </p1:arc>
    <p1:arc class="negative influence" id="tr_13" source="qual_PSEN" target="qual_EIF2AK3">
      <p1:start x="707.619" y="621.714"/>
      <p1:end x="685.6" y="688.714"/>
    </p1:arc>
    <p1:arc class="negative influence" id="tr_14" source="qual_PSEN" target="qual_ERN1">
      <p1:start x="735.619" y="621.714"/>
      <p1:end x="783.619" y="641.714"/>
    </p1:arc>
    <p1:arc class="negative influence" id="tr_15" source="qual_PSEN" target="qual_ATF6">
      <p1:start x="735.619" y="621.714"/>
      <p1:end x="859.619" y="688.714"/>
    </p1:arc>
    <p1:arc class="positive influence" id="tr_16" source="qual_NOS1" target="qual_NO">
      <p1:start x="428.86" y="813.214"/>
      <p1:end x="591.86" y="811.214"/>
    </p1:arc>
    <p1:arc class="positive influence" id="tr_17" source="qual_Ca2" target="qual_CAPN">
      <p1:start x="781.619" y="527.714"/>
      <p1:end x="414.86" y="733.6"/>
    </p1:arc>
    <p1:arc class="positive influence" id="tr_18" source="qual_CAPN" target="qual_CDK5R1">
      <p1:start x="414.86" y="760.6"/>
      <p1:end x="511.86" y="846.714"/>
    </p1:arc>
    <p1:arc class="unknown influence" id="tr_19" source="qual_CDK5R1" target="qual_CDK5R1">
      <p1:start x="525.86" y="846.714"/>
      <p1:end x="525.86" y="846.714"/>
    </p1:arc>
    <p1:arc class="unknown influence" id="tr_20" source="qual_CDK5R1" target="qual_MAPT">
      <p1:start x="553.86" y="860.214"/>
      <p1:end x="649.86" y="856.214"/>
    </p1:arc>
    <p1:arc class="unknown influence" id="tr_21" source="qual_CDK5" target="qual_MAPT">
      <p1:start x="477.86" y="907.214"/>
      <p1:end x="649.86" y="856.214"/>
    </p1:arc>
    <p1:arc class="unknown influence" id="tr_22" source="qual_GSK3B" target="qual_MAPT">
      <p1:start x="615.86" y="889.714"/>
      <p1:end x="663.86" y="869.714"/>
    </p1:arc>
    <p1:arc class="negative influence" id="tr_23" source="qual_APP" target="qual_GAPDH">
      <p1:start x="308" y="198.5"/>
      <p1:end x="328" y="185.214"/>
    </p1:arc>
    <p1:arc class="positive influence" id="tr_24" source="qual_Ins145P3" target="qual_ITPR">
      <p1:start x="509.619" y="690.6"/>
      <p1:end x="493.619" y="668.714"/>
    </p1:arc>
  </p1:map>

</p1:sbgn>
