<?xml version="1.0" encoding="UTF-8" standalone="no" ?>
<p1:sbgn xmlns:p1="http://sbgn.org/libsbgn/0.2">

  <p1:map language="activity flow">
    <p1:glyph class="nucleic acid feature" id="qual_p53_signaling_pathway" orientation="horizontal">
      <p1:label text="p53 signaling pathway"/>
      <p1:bbox h="44" w="112" x="562.815" y="711.917"/>
    </p1:glyph>
    <p1:glyph class="nucleic acid feature" id="qual_RUNX1" orientation="horizontal">
      <p1:label text="RUNX1"/>
      <p1:bbox h="27" w="56" x="753" y="758.917"/>
    </p1:glyph>
    <p1:glyph class="nucleic acid feature" id="qual_BCL2L1" orientation="horizontal">
      <p1:label text="BCL2L1"/>
      <p1:bbox h="27" w="56" x="600.667" y="47.3333"/>
    </p1:glyph>
    <p1:glyph class="nucleic acid feature" id="qual_PTPN11" orientation="horizontal">
      <p1:label text="PTPN11"/>
      <p1:bbox h="27" w="56" x="429.833" y="218.818"/>
    </p1:glyph>
    <p1:glyph class="nucleic acid feature" id="qual_BCR" orientation="horizontal">
      <p1:label text="BCR"/>
      <p1:bbox h="27" w="56" x="178.5" y="138"/>
    </p1:glyph>
    <p1:glyph class="nucleic acid feature" id="qual_TP53" orientation="horizontal">
      <p1:label text="TP53"/>
      <p1:bbox h="27" w="56" x="805.556" y="395.917"/>
    </p1:glyph>
    <p1:glyph class="nucleic acid feature" id="qual_TGFbeta_signaling_pathway" orientation="horizontal">
      <p1:label text="TGF-beta signaling pathway"/>
      <p1:bbox h="44" w="112" x="430.815" y="733"/>
    </p1:glyph>
    <p1:glyph class="nucleic acid feature" id="qual_Hematopoietic_cell_lineage" orientation="horizontal">
      <p1:label text="Hematopoietic cell lineage"/>
      <p1:bbox h="44" w="121" x="53" y="556"/>
    </p1:glyph>
    <p1:glyph class="nucleic acid feature" id="qual_Apoptosis" orientation="horizontal">
      <p1:label text="Apoptosis"/>
      <p1:bbox h="44" w="112" x="817.633" y="83"/>
    </p1:glyph>
    <p1:glyph class="nucleic acid feature" id="qual_TGFB" orientation="horizontal">
      <p1:label text="TGFB"/>
      <p1:bbox h="27" w="56" x="30.6667" y="763"/>
    </p1:glyph>
    <p1:glyph class="nucleic acid feature" id="qual_HDAC" orientation="horizontal">
      <p1:label text="HDAC"/>
      <p1:bbox h="27" w="56" x="981" y="743"/>
    </p1:glyph>
    <p1:glyph class="nucleic acid feature" id="qual_CTBP" orientation="horizontal">
      <p1:label text="CTBP"/>
      <p1:bbox h="27" w="56" x="905" y="696"/>
    </p1:glyph>
    <p1:glyph class="nucleic acid feature" id="qual_MECOM" orientation="horizontal">
      <p1:label text="MECOM"/>
      <p1:bbox h="27" w="56" x="829" y="711.917"/>
    </p1:glyph>
    <p1:glyph class="nucleic acid feature" id="qual_MYC" orientation="horizontal">
      <p1:label text="MYC"/>
      <p1:bbox h="27" w="56" x="797" y="301.917"/>
    </p1:glyph>
    <p1:glyph class="nucleic acid feature" id="qual_TGFBR2" orientation="horizontal">
      <p1:label text="TGFBR2"/>
      <p1:bbox h="27" w="56" x="182.667" y="787"/>
    </p1:glyph>
    <p1:glyph class="nucleic acid feature" id="qual_TGFBR1" orientation="horizontal">
      <p1:label text="TGFBR1"/>
      <p1:bbox h="27" w="56" x="106.667" y="740"/>
    </p1:glyph>
    <p1:glyph class="nucleic acid feature" id="qual_STAT5" orientation="horizontal">
      <p1:label text="STAT5"/>
      <p1:bbox h="27" w="56" x="201.833" y="359.818"/>
    </p1:glyph>
    <p1:glyph class="nucleic acid feature" id="qual_SMAD4" orientation="horizontal">
      <p1:label text="SMAD4"/>
      <p1:bbox h="27" w="56" x="271" y="802.5"/>
    </p1:glyph>
    <p1:glyph class="nucleic acid feature" id="qual_RELA" orientation="horizontal">
      <p1:label text="RELA"/>
      <p1:bbox h="27" w="56" x="665.633" y="154.5"/>
    </p1:glyph>
    <p1:glyph class="nucleic acid feature" id="qual_NFKBIA" orientation="horizontal">
      <p1:label text="NFKBIA"/>
      <p1:bbox h="27" w="56" x="741.633" y="107.5"/>
    </p1:glyph>
    <p1:glyph class="nucleic acid feature" id="qual_CDKN1B" orientation="horizontal">
      <p1:label text="CDKN1B"/>
      <p1:bbox h="27" w="56" x="581.833" y="190.333"/>
    </p1:glyph>
    <p1:glyph class="nucleic acid feature" id="qual_MDM2" orientation="horizontal">
      <p1:label text="MDM2"/>
      <p1:bbox h="27" w="56" x="881.556" y="348.917"/>
    </p1:glyph>
    <p1:glyph class="nucleic acid feature" id="qual_IKBKG" orientation="horizontal">
      <p1:label text="IKBKG"/>
      <p1:bbox h="27" w="56" x="589.633" y="141.333"/>
    </p1:glyph>
    <p1:glyph class="nucleic acid feature" id="qual_BAD" orientation="horizontal">
      <p1:label text="BAD"/>
      <p1:bbox h="27" w="56" x="513.633" y="94.3333"/>
    </p1:glyph>
    <p1:glyph class="nucleic acid feature" id="qual_CDKN2A" orientation="horizontal">
      <p1:label text="CDKN2A"/>
      <p1:bbox h="27" w="56" x="694.815" y="664.917"/>
    </p1:glyph>
    <p1:glyph class="nucleic acid feature" id="qual_CDKN1A" orientation="horizontal">
      <p1:label text="CDKN1A"/>
      <p1:bbox h="27" w="56" x="729.556" y="442.917"/>
    </p1:glyph>
    <p1:glyph class="nucleic acid feature" id="qual_SOS" orientation="horizontal">
      <p1:label text="SOS"/>
      <p1:bbox h="27" w="56" x="353.833" y="265.818"/>
    </p1:glyph>
    <p1:glyph class="nucleic acid feature" id="qual_GRB2" orientation="horizontal">
      <p1:label text="GRB2"/>
      <p1:bbox h="27" w="56" x="209.633" y="218.818"/>
    </p1:glyph>
    <p1:glyph class="nucleic acid feature" id="qual_SHC" orientation="horizontal">
      <p1:label text="SHC"/>
      <p1:bbox h="27" w="56" x="277.833" y="312.818"/>
    </p1:glyph>
    <p1:glyph class="nucleic acid feature" id="qual_GAB2" orientation="horizontal">
      <p1:label text="GAB2"/>
      <p1:bbox h="27" w="56" x="285.633" y="171.818"/>
    </p1:glyph>
    <p1:glyph class="nucleic acid feature" id="qual_CRK" orientation="horizontal">
      <p1:label text="CRK"/>
      <p1:bbox h="27" w="56" x="292.5" y="30.8182"/>
    </p1:glyph>
    <p1:glyph class="nucleic acid feature" id="qual_CBL" orientation="horizontal">
      <p1:label text="CBL"/>
      <p1:bbox h="27" w="56" x="216.5" y="77.8182"/>
    </p1:glyph>
    <p1:glyph class="nucleic acid feature" id="qual_Phosphatidylinositol345trisphosphate" orientation="horizontal">
      <p1:label text="Phosphatidylinositol-3,4,5-trisphosphate"/>
      <p1:bbox h="18" w="18" x="437.633" y="86.8182"/>
    </p1:glyph>
    <p1:glyph class="nucleic acid feature" id="qual_E2F" orientation="horizontal">
      <p1:label text="E2F"/>
      <p1:bbox h="27" w="56" x="1074.81" y="582"/>
    </p1:glyph>
    <p1:glyph class="nucleic acid feature" id="qual_RB1" orientation="horizontal">
      <p1:label text="RB1"/>
      <p1:bbox h="27" w="56" x="998.815" y="535"/>
    </p1:glyph>
    <p1:glyph class="nucleic acid feature" id="qual_SMAD3" orientation="horizontal">
      <p1:label text="SMAD3"/>
      <p1:bbox h="27" w="56" x="347" y="755.5"/>
    </p1:glyph>
    <p1:glyph class="nucleic acid feature" id="qual_CDK" orientation="horizontal">
      <p1:label text="CDK"/>
      <p1:bbox h="27" w="56" x="846.815" y="536.917"/>
    </p1:glyph>
    <p1:glyph class="nucleic acid feature" id="qual_CCND1" orientation="horizontal">
      <p1:label text="CCND1"/>
      <p1:bbox h="27" w="56" x="922.815" y="489.917"/>
    </p1:glyph>
    <p1:glyph class="nucleic acid feature" id="qual_MAPK_signaling_pathway" orientation="horizontal">
      <p1:label text="MAPK signaling pathway"/>
      <p1:bbox h="44" w="112" x="525.833" y="284.333"/>
    </p1:glyph>
    <p1:glyph class="nucleic acid feature" id="qual_AKT" orientation="horizontal">
      <p1:label text="AKT"/>
      <p1:bbox h="27" w="56" x="437.633" y="138"/>
    </p1:glyph>
    <p1:glyph class="nucleic acid feature" id="qual_PIK3" orientation="horizontal">
      <p1:label text="PIK3"/>
      <p1:bbox h="27" w="56" x="361.633" y="124.818"/>
    </p1:glyph>
    <p1:glyph class="nucleic acid feature" id="qual_Cell_cycle" orientation="horizontal">
      <p1:label text="Cell cycle"/>
      <p1:bbox h="44" w="112" x="998.815" y="425.917"/>
    </p1:glyph>
    <p1:glyph class="nucleic acid feature" id="qual_MAPK" orientation="horizontal">
      <p1:label text="MAPK"/>
      <p1:bbox h="27" w="56" x="733.833" y="237"/>
    </p1:glyph>
    <p1:glyph class="nucleic acid feature" id="qual_MAP2K" orientation="horizontal">
      <p1:label text="MAP2K"/>
      <p1:bbox h="27" w="56" x="657.833" y="237.333"/>
    </p1:glyph>
    <p1:glyph class="nucleic acid feature" id="qual_BRAF" orientation="horizontal">
      <p1:label text="BRAF"/>
      <p1:bbox h="27" w="56" x="505.833" y="237"/>
    </p1:glyph>
    <p1:glyph class="nucleic acid feature" id="qual_NRAS" orientation="horizontal">
      <p1:label text="NRAS"/>
      <p1:bbox h="27" w="56" x="438" y="312.818"/>
    </p1:glyph>
    <p1:glyph class="nucleic acid feature" id="qual_undefined" orientation="horizontal">
      <p1:label text="undefined"/>
      <p1:bbox h="61" w="56" x="770.815" y="583.917"/>
    </p1:glyph>
    <p1:arc class="unknown influence" id="tr_0" source="qual_PIK3" target="qual_AKT">
      <p1:start x="417.633" y="138.318"/>
      <p1:end x="437.633" y="151.5"/>
    </p1:arc>
    <p1:arc class="positive influence" id="tr_1" source="qual_undefined" target="qual_PIK3">
      <p1:start x="784.815" y="583.917"/>
      <p1:end x="403.633" y="151.818"/>
    </p1:arc>
    <p1:arc class="positive influence" id="tr_2" source="qual_BCR" target="qual_GRB2">
      <p1:start x="206.5" y="165"/>
      <p1:end x="237.633" y="218.818"/>
    </p1:arc>
    <p1:arc class="positive influence" id="tr_3" source="qual_GRB2" target="qual_GAB2">
      <p1:start x="251.633" y="218.818"/>
      <p1:end x="299.633" y="198.818"/>
    </p1:arc>
    <p1:arc class="positive influence" id="tr_4" source="qual_GAB2" target="qual_PIK3">
      <p1:start x="327.633" y="171.818"/>
      <p1:end x="375.633" y="151.818"/>
    </p1:arc>
    <p1:arc class="positive influence" id="tr_5" source="qual_GAB2" target="qual_PTPN11">
      <p1:start x="341.633" y="185.318"/>
      <p1:end x="429.833" y="232.318"/>
    </p1:arc>
    <p1:arc class="positive influence" id="tr_6" source="qual_GRB2" target="qual_SOS">
      <p1:start x="265.633" y="232.318"/>
      <p1:end x="353.833" y="279.318"/>
    </p1:arc>
    <p1:arc class="positive influence" id="tr_7" source="qual_SOS" target="qual_NRAS">
      <p1:start x="395.833" y="292.818"/>
      <p1:end x="452" y="312.818"/>
    </p1:arc>
    <p1:arc class="positive influence" id="tr_8" source="qual_NRAS" target="qual_BRAF">
      <p1:start x="480" y="312.818"/>
      <p1:end x="519.833" y="264"/>
    </p1:arc>
    <p1:arc class="positive influence" id="tr_9" source="qual_TGFB" target="qual_undefined">
      <p1:start x="86.6667" y="776.5"/>
      <p1:end x="770.815" y="614.417"/>
    </p1:arc>
    <p1:arc class="positive influence" id="tr_10" source="qual_MECOM" target="qual_undefined">
      <p1:start x="843" y="711.917"/>
      <p1:end x="812.815" y="644.917"/>
    </p1:arc>
    <p1:arc class="positive influence" id="tr_11" source="qual_RUNX1" target="qual_undefined">
      <p1:start x="781" y="758.917"/>
      <p1:end x="798.815" y="644.917"/>
    </p1:arc>
    <p1:arc class="positive influence" id="tr_12" source="qual_BCR" target="qual_undefined">
      <p1:start x="220.5" y="165"/>
      <p1:end x="784.815" y="583.917"/>
    </p1:arc>
    <p1:arc class="positive influence" id="tr_13" source="qual_AKT" target="qual_IKBKG">
      <p1:start x="493.633" y="151.5"/>
      <p1:end x="589.633" y="154.833"/>
    </p1:arc>
    <p1:arc class="positive influence" id="tr_14" source="qual_IKBKG" target="qual_NFKBIA">
      <p1:start x="645.633" y="154.833"/>
      <p1:end x="741.633" y="121"/>
    </p1:arc>
    <p1:arc class="positive influence" id="tr_15" source="qual_AKT" target="qual_MDM2">
      <p1:start x="493.633" y="151.5"/>
      <p1:end x="881.556" y="362.417"/>
    </p1:arc>
    <p1:arc class="positive influence" id="tr_16" source="qual_BCR" target="qual_SHC">
      <p1:start x="220.5" y="165"/>
      <p1:end x="291.833" y="312.818"/>
    </p1:arc>
    <p1:arc class="positive influence" id="tr_17" source="qual_BRAF" target="qual_MAP2K">
      <p1:start x="561.833" y="250.5"/>
      <p1:end x="657.833" y="250.833"/>
    </p1:arc>
    <p1:arc class="positive influence" id="tr_18" source="qual_MAP2K" target="qual_MAPK">
      <p1:start x="713.833" y="250.833"/>
      <p1:end x="733.833" y="250.5"/>
    </p1:arc>
    <p1:arc class="positive influence" id="tr_19" source="qual_undefined" target="qual_RB1">
      <p1:start x="826.815" y="614.417"/>
      <p1:end x="998.815" y="548.5"/>
    </p1:arc>
    <p1:arc class="positive influence" id="tr_20" source="qual_undefined" target="qual_SMAD3">
      <p1:start x="770.815" y="614.417"/>
      <p1:end x="403" y="769"/>
    </p1:arc>
    <p1:arc class="negative influence" id="tr_21" source="qual_AKT" target="qual_BAD">
      <p1:start x="479.633" y="138"/>
      <p1:end x="527.633" y="121.333"/>
    </p1:arc>
    <p1:arc class="negative influence" id="tr_22" source="qual_AKT" target="qual_CDKN1B">
      <p1:start x="493.633" y="151.5"/>
      <p1:end x="581.833" y="203.833"/>
    </p1:arc>
    <p1:arc class="negative influence" id="tr_23" source="qual_MDM2" target="qual_TP53">
      <p1:start x="895.556" y="375.917"/>
      <p1:end x="847.556" y="395.917"/>
    </p1:arc>
    <p1:arc class="negative influence" id="tr_24" source="qual_MDM2" target="qual_TP53">
      <p1:start x="895.556" y="375.917"/>
      <p1:end x="847.556" y="395.917"/>
    </p1:arc>
    <p1:arc class="negative influence" id="tr_25" source="qual_CDKN1A" target="qual_undefined">
      <p1:start x="757.556" y="469.917"/>
      <p1:end x="784.815" y="583.917"/>
    </p1:arc>
    <p1:arc class="unknown influence" id="tr_26" source="qual_SMAD4" target="qual_SMAD3">
      <p1:start x="313" y="802.5"/>
      <p1:end x="361" y="782.5"/>
    </p1:arc>
    <p1:arc class="positive influence" id="tr_27" source="qual_TP53" target="qual_CDKN1A">
      <p1:start x="819.556" y="422.917"/>
      <p1:end x="771.556" y="442.917"/>
    </p1:arc>
    <p1:arc class="unknown influence" id="tr_28" source="qual_RELA" target="qual_NFKBIA">
      <p1:start x="707.633" y="154.5"/>
      <p1:end x="755.633" y="134.5"/>
    </p1:arc>
    <p1:arc class="unknown influence" id="tr_29" source="qual_E2F" target="qual_RB1">
      <p1:start x="1088.81" y="582"/>
      <p1:end x="1040.81" y="562"/>
    </p1:arc>
    <p1:arc class="negative influence" id="tr_30" source="qual_BAD" target="qual_BCL2L1">
      <p1:start x="555.633" y="94.3333"/>
      <p1:end x="614.667" y="74.3333"/>
    </p1:arc>
    <p1:arc class="unknown influence" id="tr_31" source="qual_BCR" target="qual_MYC">
      <p1:start x="234.5" y="151.5"/>
      <p1:end x="797" y="315.417"/>
    </p1:arc>
    <p1:arc class="positive influence" id="tr_32" source="qual_BCR" target="qual_STAT5">
      <p1:start x="206.5" y="165"/>
      <p1:end x="229.833" y="359.818"/>
    </p1:arc>
    <p1:arc class="positive influence" id="tr_33" source="qual_STAT5" target="qual_BCL2L1">
      <p1:start x="243.833" y="359.818"/>
      <p1:end x="614.667" y="74.3333"/>
    </p1:arc>
    <p1:arc class="unknown influence" id="tr_34" source="qual_CDKN2A" target="qual_MDM2">
      <p1:start x="736.815" y="664.917"/>
      <p1:end x="895.556" y="375.917"/>
    </p1:arc>
    <p1:arc class="unknown influence" id="tr_35" source="qual_CDKN2A" target="qual_undefined">
      <p1:start x="736.815" y="664.917"/>
      <p1:end x="784.815" y="644.917"/>
    </p1:arc>
  </p1:map>

</p1:sbgn>
