<?xml version="1.0" encoding="UTF-8" standalone="no" ?>
<p1:sbgn xmlns:p1="http://sbgn.org/libsbgn/0.2">

  <p1:map language="activity flow">
    <p1:glyph class="nucleic acid feature" id="qual_Tight_junction" orientation="horizontal">
      <p1:label text="Tight junction"/>
      <p1:bbox h="35" w="125" x="687" y="109"/>
    </p1:glyph>
    <p1:glyph class="nucleic acid feature" id="qual_Retinol_metabolism" orientation="horizontal">
      <p1:label text="Retinol metabolism"/>
      <p1:bbox h="44" w="125" x="403.286" y="816.9"/>
    </p1:glyph>
    <p1:glyph class="nucleic acid feature" id="qual_Bile_secretion" orientation="horizontal">
      <p1:label text="Bile secretion"/>
      <p1:bbox h="35" w="125" x="156.333" y="817"/>
    </p1:glyph>
    <p1:glyph class="nucleic acid feature" id="qual_APOB" orientation="horizontal">
      <p1:label text="APOB"/>
      <p1:bbox h="27" w="56" x="945" y="555.933"/>
    </p1:glyph>
    <p1:glyph class="nucleic acid feature" id="qual_Triglyceride" orientation="horizontal">
      <p1:label text="Triglyceride"/>
      <p1:bbox h="18" w="18" x="897" y="612.933"/>
    </p1:glyph>
    <p1:glyph class="nucleic acid feature" id="qual_Cholesterol_ester" orientation="horizontal">
      <p1:label text="Cholesterol ester"/>
      <p1:bbox h="18" w="18" x="899.5" y="717.933"/>
    </p1:glyph>
    <p1:glyph class="nucleic acid feature" id="qual_APOA4" orientation="horizontal">
      <p1:label text="APOA4"/>
      <p1:bbox h="27" w="56" x="971" y="660.933"/>
    </p1:glyph>
    <p1:glyph class="nucleic acid feature" id="qual_APOA1" orientation="horizontal">
      <p1:label text="APOA1"/>
      <p1:bbox h="27" w="56" x="947.5" y="765.933"/>
    </p1:glyph>
    <p1:glyph class="nucleic acid feature" id="qual_Bile_salt" orientation="horizontal">
      <p1:label text="Bile salt"/>
      <p1:bbox h="18" w="18" x="108.333" y="769"/>
    </p1:glyph>
    <p1:glyph class="nucleic acid feature" id="qual_Vitamin_E" orientation="horizontal">
      <p1:label text="Vitamin E"/>
      <p1:bbox h="18" w="18" x="690" y="686"/>
    </p1:glyph>
    <p1:glyph class="nucleic acid feature" id="qual_Retinyl_ester" orientation="horizontal">
      <p1:label text="Retinyl ester"/>
      <p1:bbox h="18" w="18" x="55.75" y="624.9"/>
    </p1:glyph>
    <p1:glyph class="nucleic acid feature" id="qual_SCARB1" orientation="horizontal">
      <p1:label text="SCARB1"/>
      <p1:bbox h="27" w="56" x="533" y="750"/>
    </p1:glyph>
    <p1:glyph class="nucleic acid feature" id="qual_Retinol" orientation="horizontal">
      <p1:label text="Retinol"/>
      <p1:bbox h="18" w="18" x="724.333" y="772.5"/>
    </p1:glyph>
    <p1:glyph class="nucleic acid feature" id="qual_Tocopherol_acetate" orientation="horizontal">
      <p1:label text="Tocopherol acetate"/>
      <p1:bbox h="18" w="18" x="354.556" y="624.9"/>
    </p1:glyph>
    <p1:glyph class="nucleic acid feature" id="qual_Vitamin_E_1" orientation="horizontal">
      <p1:label text="Vitamin E"/>
      <p1:bbox h="18" w="18" x="355.286" y="768.9"/>
    </p1:glyph>
    <p1:glyph class="nucleic acid feature" id="qual_CUBN" orientation="horizontal">
      <p1:label text="CUBN"/>
      <p1:bbox h="27" w="56" x="653.75" y="237.933"/>
    </p1:glyph>
    <p1:glyph class="nucleic acid feature" id="qual_Vitamin_B12" orientation="horizontal">
      <p1:label text="Vitamin B12"/>
      <p1:bbox h="18" w="18" x="1394.62" y="277.25"/>
    </p1:glyph>
    <p1:glyph class="nucleic acid feature" id="qual_GIF" orientation="horizontal">
      <p1:label text="GIF"/>
      <p1:bbox h="27" w="56" x="903.5" y="245.933"/>
    </p1:glyph>
    <p1:glyph class="nucleic acid feature" id="qual_LMBRD1" orientation="horizontal">
      <p1:label text="LMBRD1"/>
      <p1:bbox h="27" w="56" x="1003.75" y="302.933"/>
    </p1:glyph>
    <p1:glyph class="nucleic acid feature" id="qual_ABCC1" orientation="horizontal">
      <p1:label text="ABCC1"/>
      <p1:bbox h="27" w="56" x="1136" y="297"/>
    </p1:glyph>
    <p1:glyph class="nucleic acid feature" id="qual_TCN2" orientation="horizontal">
      <p1:label text="TCN2"/>
      <p1:bbox h="27" w="56" x="1135.75" y="359.933"/>
    </p1:glyph>
    <p1:glyph class="nucleic acid feature" id="qual_MMACHC" orientation="horizontal">
      <p1:label text="MMACHC"/>
      <p1:bbox h="27" w="56" x="1031" y="236"/>
    </p1:glyph>
    <p1:glyph class="nucleic acid feature" id="qual_Endocytosis" orientation="horizontal">
      <p1:label text="Endocytosis"/>
      <p1:bbox h="35" w="102" x="871.75" y="351.933"/>
    </p1:glyph>
    <p1:glyph class="nucleic acid feature" id="qual_Lysosome" orientation="horizontal">
      <p1:label text="Lysosome"/>
      <p1:bbox h="35" w="102" x="1003.75" y="416.933"/>
    </p1:glyph>
    <p1:glyph class="nucleic acid feature" id="qual_RBP2" orientation="horizontal">
      <p1:label text="RBP2"/>
      <p1:bbox h="27" w="56" x="771.5" y="879.933"/>
    </p1:glyph>
    <p1:glyph class="nucleic acid feature" id="qual_LRAT" orientation="horizontal">
      <p1:label text="LRAT"/>
      <p1:bbox h="27" w="56" x="857.5" y="822.933"/>
    </p1:glyph>
    <p1:glyph class="nucleic acid feature" id="qual_SLC5A6" orientation="horizontal">
      <p1:label text="SLC5A6"/>
      <p1:bbox h="27" w="56" x="653.75" y="436"/>
    </p1:glyph>
    <p1:glyph class="nucleic acid feature" id="qual_SLC23A1" orientation="horizontal">
      <p1:label text="SLC23A1"/>
      <p1:bbox h="27" w="56" x="546.556" y="481.333"/>
    </p1:glyph>
    <p1:glyph class="nucleic acid feature" id="qual_SLC19A1" orientation="horizontal">
      <p1:label text="SLC19A1"/>
      <p1:bbox h="27" w="56" x="718.556" y="591"/>
    </p1:glyph>
    <p1:glyph class="nucleic acid feature" id="qual_Na" orientation="horizontal">
      <p1:label text="Na+"/>
      <p1:bbox h="18" w="18" x="450.556" y="497"/>
    </p1:glyph>
    <p1:glyph class="nucleic acid feature" id="qual_Biotin" orientation="horizontal">
      <p1:label text="Biotin"/>
      <p1:bbox h="18" w="18" x="1304.12" y="469.25"/>
    </p1:glyph>
    <p1:glyph class="nucleic acid feature" id="qual_Ascorbate" orientation="horizontal">
      <p1:label text="Ascorbate"/>
      <p1:bbox h="18" w="18" x="1208.12" y="565.25"/>
    </p1:glyph>
    <p1:glyph class="nucleic acid feature" id="qual_SLC19A" orientation="horizontal">
      <p1:label text="SLC19A"/>
      <p1:bbox h="27" w="56" x="653.75" y="344.5"/>
    </p1:glyph>
    <p1:glyph class="nucleic acid feature" id="qual_Fat_digestion_and_absorption" orientation="horizontal">
      <p1:label text="Fat digestion and absorption"/>
      <p1:bbox h="44" w="111" x="804" y="481.933"/>
    </p1:glyph>
    <p1:glyph class="nucleic acid feature" id="qual_Thiamin" orientation="horizontal">
      <p1:label text="Thiamin"/>
      <p1:bbox h="18" w="18" x="1298.62" y="373.25"/>
    </p1:glyph>
    <p1:glyph class="nucleic acid feature" id="qual_TPP" orientation="horizontal">
      <p1:label text="TPP"/>
      <p1:bbox h="18" w="18" x="337.833" y="136.9"/>
    </p1:glyph>
    <p1:glyph class="nucleic acid feature" id="qual_FMN" orientation="horizontal">
      <p1:label text="FMN"/>
      <p1:bbox h="18" w="18" x="233.267" y="218.5"/>
    </p1:glyph>
    <p1:glyph class="nucleic acid feature" id="qual_FAD" orientation="horizontal">
      <p1:label text="FAD"/>
      <p1:bbox h="18" w="18" x="281.267" y="266.5"/>
    </p1:glyph>
    <p1:glyph class="nucleic acid feature" id="qual_Riboflavin" orientation="horizontal">
      <p1:label text="Riboflavin"/>
      <p1:bbox h="18" w="18" x="1250.62" y="421.25"/>
    </p1:glyph>
    <p1:glyph class="nucleic acid feature" id="qual_Biocytin" orientation="horizontal">
      <p1:label text="Biocytin"/>
      <p1:bbox h="18" w="18" x="157.833" y="228.5"/>
    </p1:glyph>
    <p1:glyph class="nucleic acid feature" id="qual_BTD" orientation="horizontal">
      <p1:label text="BTD"/>
      <p1:bbox h="27" w="56" x="227" y="324"/>
    </p1:glyph>
    <p1:glyph class="nucleic acid feature" id="qual_Biotin_1" orientation="horizontal">
      <p1:label text="Biotin"/>
      <p1:bbox h="18" w="18" x="201" y="426"/>
    </p1:glyph>
    <p1:glyph class="nucleic acid feature" id="qual_Pyridoxamine_phosphate" orientation="horizontal">
      <p1:label text="Pyridoxamine phosphate"/>
      <p1:bbox h="18" w="18" x="377.267" y="258.9"/>
    </p1:glyph>
    <p1:glyph class="nucleic acid feature" id="qual_PM" orientation="horizontal">
      <p1:label text="PM"/>
      <p1:bbox h="18" w="18" x="387.75" y="354.9"/>
    </p1:glyph>
    <p1:glyph class="nucleic acid feature" id="qual_CoA" orientation="horizontal">
      <p1:label text="CoA"/>
      <p1:bbox h="18" w="18" x="172" y="300"/>
    </p1:glyph>
    <p1:glyph class="nucleic acid feature" id="qual_Pantothenate" orientation="horizontal">
      <p1:label text="Pantothenate"/>
      <p1:bbox h="18" w="18" x="1256.12" y="517.25"/>
    </p1:glyph>
    <p1:glyph class="nucleic acid feature" id="qual_FOLH1" orientation="horizontal">
      <p1:label text="FOLH1"/>
      <p1:bbox h="27" w="56" x="59" y="388"/>
    </p1:glyph>
    <p1:glyph class="nucleic acid feature" id="qual_Folate" orientation="horizontal">
      <p1:label text="Folate"/>
      <p1:bbox h="18" w="18" x="450.556" y="586.333"/>
    </p1:glyph>
    <p1:glyph class="nucleic acid feature" id="qual_NAD" orientation="horizontal">
      <p1:label text="NAD"/>
      <p1:bbox h="18" w="18" x="115" y="300"/>
    </p1:glyph>
    <p1:glyph class="nucleic acid feature" id="qual_Vitamin_PP" orientation="horizontal">
      <p1:label text="Vitamin PP"/>
      <p1:bbox h="18" w="18" x="1160.12" y="613.25"/>
    </p1:glyph>
    <p1:glyph class="nucleic acid feature" id="qual_Vitamin_D3" orientation="horizontal">
      <p1:label text="Vitamin D3"/>
      <p1:bbox h="18" w="18" x="306.556" y="624.9"/>
    </p1:glyph>
    <p1:glyph class="nucleic acid feature" id="qual_Vitamin_K1" orientation="horizontal">
      <p1:label text="Vitamin K1"/>
      <p1:bbox h="18" w="18" x="402.556" y="576.9"/>
    </p1:glyph>
    <p1:glyph class="nucleic acid feature" id="qual_Menadione" orientation="horizontal">
      <p1:label text="Menadione"/>
      <p1:bbox h="18" w="18" x="403.286" y="720.9"/>
    </p1:glyph>
    <p1:glyph class="nucleic acid feature" id="qual_Vitamin_K2" orientation="horizontal">
      <p1:label text="Vitamin K2"/>
      <p1:bbox h="18" w="18" x="451.286" y="672.9"/>
    </p1:glyph>
    <p1:glyph class="nucleic acid feature" id="qual_Lysophosphatidate" orientation="horizontal">
      <p1:label text="Lysophosphatidate"/>
      <p1:bbox h="18" w="18" x="60.3333" y="721"/>
    </p1:glyph>
    <p1:glyph class="nucleic acid feature" id="qual_Glyceride" orientation="horizontal">
      <p1:label text="Glyceride"/>
      <p1:bbox h="18" w="18" x="-40.25" y="673"/>
    </p1:glyph>
    <p1:glyph class="nucleic acid feature" id="qual_Retinol_1" orientation="horizontal">
      <p1:label text="Retinol"/>
      <p1:bbox h="18" w="18" x="135.286" y="676"/>
    </p1:glyph>
    <p1:glyph class="nucleic acid feature" id="qual_Fatty_acid" orientation="horizontal">
      <p1:label text="Fatty acid"/>
      <p1:bbox h="18" w="18" x="7.75" y="625"/>
    </p1:glyph>
    <p1:glyph class="nucleic acid feature" id="qual_Cholesterol" orientation="horizontal">
      <p1:label text="Cholesterol"/>
      <p1:bbox h="18" w="18" x="198" y="759"/>
    </p1:glyph>
    <p1:glyph class="nucleic acid feature" id="qual_C20orf54" orientation="horizontal">
      <p1:label text="C20orf54"/>
      <p1:bbox h="27" w="56" x="567.75" y="401.5"/>
    </p1:glyph>
    <p1:glyph class="nucleic acid feature" id="qual_PLP" orientation="horizontal">
      <p1:label text="PLP"/>
      <p1:bbox h="18" w="18" x="1346.62" y="325.25"/>
    </p1:glyph>
    <p1:glyph class="nucleic acid feature" id="qual_Pyridoxal" orientation="horizontal">
      <p1:label text="Pyridoxal"/>
      <p1:bbox h="18" w="18" x="329.267" y="306.9"/>
    </p1:glyph>
    <p1:glyph class="nucleic acid feature" id="qual_Pantothenate_and_CoA_biosynthesis" orientation="horizontal">
      <p1:label text="Pantothenate and CoA biosynthesis"/>
      <p1:bbox h="44" w="120" x="285.75" y="476.9"/>
    </p1:glyph>
    <p1:glyph class="nucleic acid feature" id="qual_Riboflavin_metabolism" orientation="horizontal">
      <p1:label text="Riboflavin metabolism"/>
      <p1:bbox h="44" w="102" x="435.75" y="402.9"/>
    </p1:glyph>
    <p1:glyph class="nucleic acid feature" id="qual_Thiamine_metabolism" orientation="horizontal">
      <p1:label text="Thiamine metabolism"/>
      <p1:bbox h="44" w="102" x="385.833" y="62.9"/>
    </p1:glyph>
    <p1:glyph class="nucleic acid feature" id="qual_Biotin_metabolism" orientation="horizontal">
      <p1:label text="Biotin metabolism"/>
      <p1:bbox h="44" w="102" x="205.833" y="62.9"/>
    </p1:glyph>
    <p1:glyph class="nucleic acid feature" id="qual_Folate_biosynthesis" orientation="horizontal">
      <p1:label text="Folate biosynthesis"/>
      <p1:bbox h="44" w="102" x="25.8333" y="154.5"/>
    </p1:glyph>
    <p1:glyph class="nucleic acid feature" id="qual_Nicotinate_and_nicotinamide_metabolism" orientation="horizontal">
      <p1:label text="Nicotinate and nicotinamide metabolism"/>
      <p1:bbox h="44" w="152" x="103.75" y="550.9"/>
    </p1:glyph>
    <p1:glyph class="nucleic acid feature" id="qual_betaCarotene" orientation="horizontal">
      <p1:label text="beta-Carotene"/>
      <p1:bbox h="18" w="18" x="481" y="747"/>
    </p1:glyph>
    <p1:glyph class="nucleic acid feature" id="qual_Retinal" orientation="horizontal">
      <p1:label text="Retinal"/>
      <p1:bbox h="18" w="18" x="676.333" y="749"/>
    </p1:glyph>
    <p1:glyph class="nucleic acid feature" id="qual_Vitamin_B6_metabolism" orientation="horizontal">
      <p1:label text="Vitamin B6 metabolism"/>
      <p1:bbox h="44" w="102" x="425.267" y="184.9"/>
    </p1:glyph>
    <p1:glyph class="nucleic acid feature" id="qual_AWAT2" orientation="horizontal">
      <p1:label text="AWAT2"/>
      <p1:bbox h="27" w="56" x="772.333" y="715.5"/>
    </p1:glyph>
    <p1:glyph class="nucleic acid feature" id="qual_SLC46A1" orientation="horizontal">
      <p1:label text="SLC46A1"/>
      <p1:bbox h="27" w="56" x="632.556" y="534"/>
    </p1:glyph>
    <p1:glyph class="nucleic acid feature" id="qual_H" orientation="horizontal">
      <p1:label text="H+"/>
      <p1:bbox h="18" w="18" x="498.556" y="538.333"/>
    </p1:glyph>
    <p1:glyph class="nucleic acid feature" id="qual_PNLIP" orientation="horizontal">
      <p1:label text="PNLIP"/>
      <p1:bbox h="27" w="56" x="183.286" y="672.9"/>
    </p1:glyph>
    <p1:glyph class="nucleic acid feature" id="qual_PLB1" orientation="horizontal">
      <p1:label text="PLB1"/>
      <p1:bbox h="27" w="56" x="269.286" y="729.9"/>
    </p1:glyph>
    <p1:glyph class="nucleic acid feature" id="qual_undefined" orientation="horizontal">
      <p1:label text="undefined"/>
      <p1:bbox h="27" w="102" x="739.75" y="294.933"/>
    </p1:glyph>
    <p1:arc class="unknown influence" id="tr_0" source="qual_Vitamin_B12" target="qual_GIF">
      <p1:start x="1394.62" y="286.25"/>
      <p1:end x="959.5" y="259.433"/>
    </p1:arc>
    <p1:arc class="unknown influence" id="tr_1" source="qual_Vitamin_B12" target="qual_undefined">
      <p1:start x="1394.62" y="286.25"/>
      <p1:end x="841.75" y="308.433"/>
    </p1:arc>
    <p1:arc class="unknown influence" id="tr_2" source="qual_Vitamin_B12" target="qual_MMACHC">
      <p1:start x="1394.62" y="286.25"/>
      <p1:end x="1087" y="249.5"/>
    </p1:arc>
    <p1:arc class="unknown influence" id="tr_3" source="qual_Retinol" target="qual_RBP2">
      <p1:start x="737.833" y="790.5"/>
      <p1:end x="785.5" y="879.933"/>
    </p1:arc>
  </p1:map>

</p1:sbgn>
